mseep_python_server_mcp-0.1.2.dist-info/licenses/LICENSE
src/__init__.py
src/mcp_server.py
src/server.py
mseep_python_server_mcp-0.1.2.dist-info/METADATA
mseep_python_server_mcp-0.1.2.dist-info/WHEEL
mseep_python_server_mcp-0.1.2.dist-info/top_level.txt
mseep_python_server_mcp-0.1.2.dist-info/RECORD
